pycrysfml/__init__.py
pycrysfml/api.py
pycrysfml/io.py
pycrysfml/structures.py
pycrysfml-0.1.0.dist-info/METADATA
pycrysfml-0.1.0.dist-info/WHEEL
pycrysfml-0.1.0.dist-info/top_level.txt
pycrysfml-0.1.0.dist-info/RECORD
