Metadata-Version: 2.4
Name: pycrysfml
Version: 0.1.0
Summary: Python bindings for CrysFML2008 crystallographic library
Author-email: William Ratcliff <william.ratcliff@nist.gov>
Maintainer-email: William Ratcliff <william.ratcliff@nist.gov>
License: LGPL-3.0-or-later
Project-URL: Homepage, https://github.com/scattering/pycrysfml
Project-URL: Documentation, https://github.com/scattering/pycrysfml#readme
Project-URL: Repository, https://github.com/scattering/pycrysfml.git
Project-URL: Issues, https://github.com/scattering/pycrysfml/issues
Keywords: crystallography,diffraction,neutron scattering,x-ray diffraction,space groups,magnetic structures,CrysFML
Classifier: Development Status :: 3 - Alpha
Classifier: Intended Audience :: Science/Research
Classifier: License :: OSI Approved :: GNU Lesser General Public License v3 or later (LGPLv3+)
Classifier: Operating System :: MacOS
Classifier: Operating System :: POSIX :: Linux
Classifier: Programming Language :: Python :: 3
Classifier: Programming Language :: Python :: 3.9
Classifier: Programming Language :: Python :: 3.10
Classifier: Programming Language :: Python :: 3.11
Classifier: Programming Language :: Python :: 3.12
Classifier: Programming Language :: Fortran
Classifier: Topic :: Scientific/Engineering :: Chemistry
Classifier: Topic :: Scientific/Engineering :: Physics
Requires-Python: >=3.9
Requires-Dist: numpy>=1.20.0
Requires-Dist: gfort2py>=2.6.0
Provides-Extra: dev
Requires-Dist: pytest>=7.0.0; extra == "dev"
Requires-Dist: pytest-cov>=4.0.0; extra == "dev"
Requires-Dist: black>=23.0.0; extra == "dev"
Requires-Dist: isort>=5.12.0; extra == "dev"
Requires-Dist: mypy>=1.0.0; extra == "dev"
Provides-Extra: docs
Requires-Dist: sphinx>=6.0.0; extra == "docs"
Requires-Dist: sphinx-rtd-theme>=1.2.0; extra == "docs"
Requires-Dist: myst-parser>=1.0.0; extra == "docs"
